inventory_md/__init__.py
inventory_md/_version.py
inventory_md/api_server.py
inventory_md/cli.py
inventory_md/parser.py
inventory_md/shopping_list.py
inventory_md/templates/aliases.json.template
inventory_md/templates/search.html
inventory_md-0.3.2.dist-info/METADATA
inventory_md-0.3.2.dist-info/WHEEL
inventory_md-0.3.2.dist-info/entry_points.txt
inventory_md-0.3.2.dist-info/RECORD
