Metadata-Version: 2.4
Name: inventory-md
Version: 0.3.2
Summary: A flexible markdown-based inventory management system
Project-URL: Repository, https://github.com/tobixen/inventory-md
Project-URL: Issues, https://github.com/tobixen/inventory-md/issues
Author-email: Tobias Brox <tobias@tobixen.no>
License-Expression: GPL-3.0-or-later
Classifier: Development Status :: 4 - Beta
Classifier: License :: OSI Approved :: GNU General Public License v3 or later (GPLv3+)
Classifier: Programming Language :: Python
Classifier: Programming Language :: Python :: 3.10
Classifier: Programming Language :: Python :: 3.11
Classifier: Programming Language :: Python :: 3.12
Classifier: Programming Language :: Python :: 3.13
Classifier: Programming Language :: Python :: 3.14
Classifier: Topic :: Database
Classifier: Topic :: Home Automation
Requires-Python: >=3.10
Requires-Dist: pillow>=10.0.0
Provides-Extra: barcode
Requires-Dist: pyzbar; extra == 'barcode'
Provides-Extra: chat
Requires-Dist: anthropic>=0.39.0; extra == 'chat'
Requires-Dist: fastapi>=0.104.0; extra == 'chat'
Requires-Dist: python-multipart>=0.0.6; extra == 'chat'
Requires-Dist: uvicorn[standard]>=0.24.0; extra == 'chat'
Provides-Extra: dev
Requires-Dist: pre-commit>=4.0; extra == 'dev'
Requires-Dist: pytest>=8.0; extra == 'dev'
Requires-Dist: ruff>=0.8; extra == 'dev'
Provides-Extra: ocr
Requires-Dist: easyocr>=1.7.0; extra == 'ocr'
